sqlite_ner/ner.py
sqlite_ner-0.1.0.dist-info/METADATA
sqlite_ner-0.1.0.dist-info/WHEEL
sqlite_ner-0.1.0.dist-info/entry_points.txt
sqlite_ner-0.1.0.dist-info/RECORD
