Metadata-Version: 2.1
Name: sqlite-ner
Version: 0.1.0
Summary: Create a new table with entities extracted from source columns
Author: redraw
Author-email: redraw@sdf.org
Requires-Python: >=3.9,<4.0
Classifier: Programming Language :: Python :: 3
Classifier: Programming Language :: Python :: 3.9
Classifier: Programming Language :: Python :: 3.10
Classifier: Programming Language :: Python :: 3.11
Requires-Dist: spacy (>=3.5.4,<4.0.0)
Requires-Dist: sqlite-utils (>=3.33,<4.0)
